{
  "trackers": [
    {
      "type": "unknown",
      "url": "https://oos.cloudgouv-eu-west-1.outscale.com/erecrutement-anssi-production/organizations/operator_logos/893/049/fa-/original/20180613_logo_anssi_m.png"
    },
    {
      "type": "unknown",
      "url": "https://oos.cloudgouv-eu-west-1.outscale.com/erecrutement-anssi-production/organizations/image_backgrounds/893/049/fa-/original/20210315_np_anssi_visuel_plateforme_rh_1200x800_v1a.jpg"
    },
    {
      "type": "unknown",
      "url": "https://oos.cloudgouv-eu-west-1.outscale.com/erecrutement-anssi-production/organizations/testimony_logos/893/049/fa-/original/Ga%C3%ABlle.PNG"
    }
  ],
  "cookies": [
    {
      "name": "_civilsdeladefense_session",
      "value": "Uhb60kZB%2FVRBjfxIk2XI1Ml4GbOnrwvx98qDqrv%2BxJJHROdm3DdQE1wM7uB5DsKUx4nzd3XHDJrMJ9RLVxzDav25Al8NyzIt2BDpXv%2BtCFffu%2Fc4fukIVbj0d7VoOTKi7uTzVwu1pclgV9zcCJ297DrUOBHai9I5lakhd2s9okZ%2BoNfZQkWcgpS3%2FHCbQCxdv0FHMeVra9Mlq4wJXsNhCrpksflrg5JvwvdAOuD5wucMUnjcrTSq9YGIF93EWHGwuvHWi9zUqIQIDcA911Iq0%2BmDstzm%2F9N9fwaPL0XOcDuGYw%3D%3D--awmLK4XmzLNJO1HV--dBJpzbGGNMRV8iYvAXT1rw%3D%3D",
      "domain": "talents.ssi.gouv.fr",
      "path": "/",
      "expires": -1,
      "size": 398,
      "httpOnly": true,
      "secure": true,
      "session": true,
      "sameSite": "Lax",
      "sameParty": false,
      "sourceScheme": "Secure",
      "sourcePort": 443
    }
  ],
  "headers": {
    "cache-control": "max-age=0, private, must-revalidate",
    "content-encoding": "gzip",
    "content-type": "text/html; charset=utf-8",
    "date": "Sun, 21 Jul 2024 07:59:05 GMT",
    "etag": "W/\"c77f2137239e9f137559ff25653ef273\"",
    "link": "</assets/application-729d2216bd2392815d7a98b303b9f7bbc2734e4235b1e80f560c5cf521fc9429.css>; rel=preload; as=style; nopush",
    "referrer-policy": "strict-origin-when-cross-origin",
    "set-cookie": "_civilsdeladefense_session=Uhb60kZB%2FVRBjfxIk2XI1Ml4GbOnrwvx98qDqrv%2BxJJHROdm3DdQE1wM7uB5DsKUx4nzd3XHDJrMJ9RLVxzDav25Al8NyzIt2BDpXv%2BtCFffu%2Fc4fukIVbj0d7VoOTKi7uTzVwu1pclgV9zcCJ297DrUOBHai9I5lakhd2s9okZ%2BoNfZQkWcgpS3%2FHCbQCxdv0FHMeVra9Mlq4wJXsNhCrpksflrg5JvwvdAOuD5wucMUnjcrTSq9YGIF93EWHGwuvHWi9zUqIQIDcA911Iq0%2BmDstzm%2F9N9fwaPL0XOcDuGYw%3D%3D--awmLK4XmzLNJO1HV--dBJpzbGGNMRV8iYvAXT1rw%3D%3D; path=/; secure; httponly; SameSite=Lax",
    "strict-transport-security": "max-age=31536000\nmax-age=31556952; preload",
    "x-content-type-options": "nosniff",
    "x-frame-options": "SAMEORIGIN",
    "x-permitted-cross-domain-policies": "none",
    "x-request-id": "d5def00c-81df-4c1e-ba42-1761a6eb74f5\nd5def00c-81df-4c1e-ba42-1761a6eb74f5",
    "x-runtime": "0.058551",
    "x-xss-protection": "0"
  },
  "endpoints": [
    {
      "hostname": "talents.ssi.gouv.fr",
      "ip": "185.21.194.105",
      "geoip": {
        "continent": {
          "code": "EU",
          "geoname_id": 6255148,
          "names": {
            "de": "Europa",
            "en": "Europe",
            "es": "Europa",
            "fr": "Europe",
            "ja": "ヨーロッパ",
            "pt-BR": "Europa",
            "ru": "Европа",
            "zh-CN": "欧洲"
          }
        },
        "country": {
          "geoname_id": 3017382,
          "is_in_european_union": true,
          "iso_code": "FR",
          "names": {
            "de": "Frankreich",
            "en": "France",
            "es": "Francia",
            "fr": "France",
            "ja": "フランス共和国",
            "pt-BR": "França",
            "ru": "Франция",
            "zh-CN": "法国"
          }
        },
        "location": {
          "accuracy_radius": 500,
          "latitude": 48.8582,
          "longitude": 2.3387,
          "time_zone": "Europe/Paris"
        },
        "registered_country": {
          "geoname_id": 3017382,
          "is_in_european_union": true,
          "iso_code": "FR",
          "names": {
            "de": "Frankreich",
            "en": "France",
            "es": "Francia",
            "fr": "France",
            "ja": "フランス共和国",
            "pt-BR": "França",
            "ru": "Франция",
            "zh-CN": "法国"
          }
        }
      }
    },
    {
      "hostname": "oos.cloudgouv-eu-west-1.outscale.com",
      "ip": "185.21.194.76",
      "geoip": {
        "continent": {
          "code": "EU",
          "geoname_id": 6255148,
          "names": {
            "de": "Europa",
            "en": "Europe",
            "es": "Europa",
            "fr": "Europe",
            "ja": "ヨーロッパ",
            "pt-BR": "Europa",
            "ru": "Европа",
            "zh-CN": "欧洲"
          }
        },
        "country": {
          "geoname_id": 3017382,
          "is_in_european_union": true,
          "iso_code": "FR",
          "names": {
            "de": "Frankreich",
            "en": "France",
            "es": "Francia",
            "fr": "France",
            "ja": "フランス共和国",
            "pt-BR": "França",
            "ru": "Франция",
            "zh-CN": "法国"
          }
        },
        "location": {
          "accuracy_radius": 500,
          "latitude": 48.8582,
          "longitude": 2.3387,
          "time_zone": "Europe/Paris"
        },
        "registered_country": {
          "geoname_id": 3017382,
          "is_in_european_union": true,
          "iso_code": "FR",
          "names": {
            "de": "Frankreich",
            "en": "France",
            "es": "Francia",
            "fr": "France",
            "ja": "フランス共和国",
            "pt-BR": "França",
            "ru": "Франция",
            "zh-CN": "法国"
          }
        }
      }
    }
  ]
}
